phoenix6-26.1.0.data/purelib/phoenix6/__init__.py
phoenix6-26.1.0.data/purelib/phoenix6/all_timestamps.py
phoenix6-26.1.0.data/purelib/phoenix6/base_status_signal.py
phoenix6-26.1.0.data/purelib/phoenix6/canbus.py
phoenix6-26.1.0.data/purelib/phoenix6/error_reporting.py
phoenix6-26.1.0.data/purelib/phoenix6/hoot_auto_replay.py
phoenix6-26.1.0.data/purelib/phoenix6/hoot_replay.py
phoenix6-26.1.0.data/purelib/phoenix6/hoot_schema_type.py
phoenix6-26.1.0.data/purelib/phoenix6/orchestra.py
phoenix6-26.1.0.data/purelib/phoenix6/phoenix_native.py
phoenix6-26.1.0.data/purelib/phoenix6/py.typed
phoenix6-26.1.0.data/purelib/phoenix6/signal_logger.py
phoenix6-26.1.0.data/purelib/phoenix6/status_code.py
phoenix6-26.1.0.data/purelib/phoenix6/status_signal.py
phoenix6-26.1.0.data/purelib/phoenix6/status_signal_collection.py
phoenix6-26.1.0.data/purelib/phoenix6/timestamp.py
phoenix6-26.1.0.data/purelib/phoenix6/units.py
phoenix6-26.1.0.data/purelib/phoenix6/unmanaged.py
phoenix6-26.1.0.data/purelib/phoenix6/utils.py
phoenix6-26.1.0.data/purelib/phoenix6/configs/__init__.py
phoenix6-26.1.0.data/purelib/phoenix6/configs/cancoder_configs.py
phoenix6-26.1.0.data/purelib/phoenix6/configs/candi_configs.py
phoenix6-26.1.0.data/purelib/phoenix6/configs/candle_configs.py
phoenix6-26.1.0.data/purelib/phoenix6/configs/canrange_configs.py
phoenix6-26.1.0.data/purelib/phoenix6/configs/config_groups.py
phoenix6-26.1.0.data/purelib/phoenix6/configs/parent_configurator.py
phoenix6-26.1.0.data/purelib/phoenix6/configs/pigeon2_configs.py
phoenix6-26.1.0.data/purelib/phoenix6/configs/talon_fx_configs.py
phoenix6-26.1.0.data/purelib/phoenix6/configs/talon_fxs_configs.py
phoenix6-26.1.0.data/purelib/phoenix6/controls/__init__.py
phoenix6-26.1.0.data/purelib/phoenix6/controls/coast_out.py
phoenix6-26.1.0.data/purelib/phoenix6/controls/color_flow_animation.py
phoenix6-26.1.0.data/purelib/phoenix6/controls/differential_duty_cycle.py
phoenix6-26.1.0.dist-info/METADATA
phoenix6-26.1.0.dist-info/WHEEL
phoenix6-26.1.0.dist-info/top_level.txt
phoenix6-26.1.0.dist-info/RECORD
