Metadata-Version: 2.4
Name: phoenix6
Version: 26.1.0
Summary: Phoenix 6 Libraries
Home-page: https://ctr-electronics.com
Author: CTR Electronics
Author-email: support@ctr-electronics.com
Project-URL: Bug Reports, https://github.com/CrossTheRoadElec/Phoenix-Releases
Keywords: CTRE,CTR Electronics,Phoenix,Phoenix 6,FRC,FIRST,robotpy,robotpy-ctre,FIRST Robotics Competition,WPILib,WPI
Classifier: Development Status :: 5 - Production/Stable
Classifier: Intended Audience :: Developers
Classifier: Topic :: Software Development :: Build Tools
Classifier: Programming Language :: Python :: 3
Classifier: Programming Language :: Python :: 3.10
Classifier: Programming Language :: Python :: 3.11
Classifier: Programming Language :: Python :: 3.12
Classifier: Programming Language :: Python :: 3.13
Requires-Python: >=3.10, <4
Requires-Dist: importlib_resources
Dynamic: author
Dynamic: author-email
Dynamic: classifier
Dynamic: description
Dynamic: description-content-type
Dynamic: home-page
Dynamic: keywords
Dynamic: project-url
Dynamic: requires-dist
Dynamic: requires-python
Dynamic: summary
